four_d_are/__init__.py
four_d_are/agent.py
four_d_are/cli.py
four_d_are/config.py
four_d_are/prompts.py
four_d_are/schemas.py
four_d_are-0.1.0.dist-info/METADATA
four_d_are-0.1.0.dist-info/WHEEL
four_d_are-0.1.0.dist-info/entry_points.txt
four_d_are-0.1.0.dist-info/licenses/LICENSE
four_d_are-0.1.0.dist-info/RECORD
