Metadata-Version: 2.4
Name: four-d-are
Version: 0.1.0
Summary: Attribution-Driven Agent Requirements Engineering for LLMs - Build agents that explain why, not just what
Project-URL: Homepage, https://github.com/anthropics/4D-ARE
Project-URL: Documentation, https://github.com/anthropics/4D-ARE#readme
Project-URL: Repository, https://github.com/anthropics/4D-ARE
Project-URL: Changelog, https://github.com/anthropics/4D-ARE/blob/main/CHANGELOG.md
Project-URL: Issues, https://github.com/anthropics/4D-ARE/issues
Author-email: Bo Yu <evenyu@tencent.com>, Lei Zhao <sanshizhao@tencent.com>
License: MIT
License-File: LICENSE
Keywords: agents,ai-agents,causal-attribution,llm,mcp,prompt-engineering,requirements-engineering
Classifier: Development Status :: 4 - Beta
Classifier: Intended Audience :: Developers
Classifier: Intended Audience :: Science/Research
Classifier: License :: OSI Approved :: MIT License
Classifier: Operating System :: OS Independent
Classifier: Programming Language :: Python :: 3
Classifier: Programming Language :: Python :: 3.10
Classifier: Programming Language :: Python :: 3.11
Classifier: Programming Language :: Python :: 3.12
Classifier: Topic :: Scientific/Engineering :: Artificial Intelligence
Requires-Python: >=3.10
Requires-Dist: openai>=1.0.0
Requires-Dist: pydantic-settings>=2.0.0
Requires-Dist: pydantic>=2.0.0
Requires-Dist: python-dotenv>=1.0.0
Requires-Dist: rich>=13.0.0
Requires-Dist: typer>=0.9.0
Provides-Extra: all
Requires-Dist: openpyxl>=3.0.0; extra == 'all'
Requires-Dist: pandas>=2.0.0; extra == 'all'
Requires-Dist: psycopg2-binary>=2.9.0; extra == 'all'
Requires-Dist: pymysql>=1.0.0; extra == 'all'
Requires-Dist: sqlalchemy>=2.0.0; extra == 'all'
Provides-Extra: dev
Requires-Dist: mypy>=1.0.0; extra == 'dev'
Requires-Dist: pre-commit>=3.0.0; extra == 'dev'
Requires-Dist: pytest-cov>=4.0.0; extra == 'dev'
Requires-Dist: pytest>=7.0.0; extra == 'dev'
Requires-Dist: ruff>=0.1.0; extra == 'dev'
Provides-Extra: excel
Requires-Dist: openpyxl>=3.0.0; extra == 'excel'
Requires-Dist: pandas>=2.0.0; extra == 'excel'
Provides-Extra: mysql
Requires-Dist: pymysql>=1.0.0; extra == 'mysql'
Requires-Dist: sqlalchemy>=2.0.0; extra == 'mysql'
Provides-Extra: postgres
Requires-Dist: psycopg2-binary>=2.9.0; extra == 'postgres'
Requires-Dist: sqlalchemy>=2.0.0; extra == 'postgres'
